pantsbuild.pants.contrib.python.checks.checker-1.29.0-py3.6-nspkg.pth
pants/contrib/python/checks/checker/__init__.py
pants/contrib/python/checks/checker/checker.py
pants/contrib/python/checks/checker/class_factoring.py
pants/contrib/python/checks/checker/common.py
pants/contrib/python/checks/checker/constant_logic.py
pants/contrib/python/checks/checker/except_statements.py
pants/contrib/python/checks/checker/file_excluder.py
pants/contrib/python/checks/checker/future_compatibility.py
pants/contrib/python/checks/checker/import_order.py
pants/contrib/python/checks/checker/indentation.py
pants/contrib/python/checks/checker/missing_contextmanager.py
pants/contrib/python/checks/checker/new_style_classes.py
pants/contrib/python/checks/checker/newlines.py
pants/contrib/python/checks/checker/print_statements.py
pants/contrib/python/checks/checker/pycodestyle.py
pants/contrib/python/checks/checker/pyflakes.py
pants/contrib/python/checks/checker/trailing_whitespace.py
pants/contrib/python/checks/checker/variable_names.py
pantsbuild.pants.contrib.python.checks.checker-1.29.0.dist-info/METADATA
pantsbuild.pants.contrib.python.checks.checker-1.29.0.dist-info/RECORD
pantsbuild.pants.contrib.python.checks.checker-1.29.0.dist-info/WHEEL
pantsbuild.pants.contrib.python.checks.checker-1.29.0.dist-info/entry_points.txt
pantsbuild.pants.contrib.python.checks.checker-1.29.0.dist-info/namespace_packages.txt
pantsbuild.pants.contrib.python.checks.checker-1.29.0.dist-info/top_level.txt
pantsbuild.pants.contrib.python.checks.checker-1.29.0.dist-info/zip-safe
