Metadata-Version: 2.1
Name: pantsbuild.pants.contrib.python.checks.checker
Version: 1.29.0
Summary: The Pants Python source code lint tool.
Home-page: https://github.com/pantsbuild/pants
License: Apache License, Version 2.0
Project-URL: Documentation, https://www.pantsbuild.org/
Project-URL: Source, https://github.com/pantsbuild/pants
Project-URL: Tracker, https://github.com/pantsbuild/pants/issues
Platform: UNKNOWN
Classifier: Intended Audience :: Developers
Classifier: License :: OSI Approved :: Apache Software License
Classifier: Operating System :: MacOS :: MacOS X
Classifier: Operating System :: POSIX :: Linux
Classifier: Programming Language :: Python
Classifier: Topic :: Software Development :: Build Tools
Requires-Dist: pycodestyle (==2.4.0)
Requires-Dist: pyflakes (==2.1.1)
Requires-Dist: six (<2,>=1.9.0)
